os_util/__init__.py
os_util/cli.py
os_util/os_util.py
os_util/result.py
os_util-0.1.1.dist-info/entry_points.txt
os_util-0.1.1.dist-info/WHEEL
os_util-0.1.1.dist-info/METADATA
os_util-0.1.1.dist-info/RECORD
